FELDSHAM/__init__.py
FELDSHAM/secret_reconstructor.py
FELDSHAM/share_generator.py
FELDSHAM/share_verifier.py
FELDSHAM/testf.py
FELDSHAM/utills.py
feldman_shamir_secret_sharing-0.0.5.dist-info/licenses/LICENSE.txt
feldman_shamir_secret_sharing-0.0.5.dist-info/METADATA
feldman_shamir_secret_sharing-0.0.5.dist-info/WHEEL
feldman_shamir_secret_sharing-0.0.5.dist-info/top_level.txt
feldman_shamir_secret_sharing-0.0.5.dist-info/RECORD
