Metadata-Version: 2.4
Name: feldman-shamir-secret-sharing
Version: 0.0.5
Summary: Реализация схемы разделения секрета Фельдмана-Шамира
Author: Alexander
Author-email: lloollfox@mail.ru
License: MIT
Project-URL: Source Repository, https://github.com/A-Sharan1/
Classifier: Programming Language :: Python :: 3
Classifier: License :: OSI Approved :: MIT License
Classifier: Operating System :: OS Independent
Requires-Python: >=3.7
License-File: LICENSE.txt
Requires-Dist: sympy>=1.7
Dynamic: author
Dynamic: author-email
Dynamic: classifier
Dynamic: description
Dynamic: description-content-type
Dynamic: license
Dynamic: license-file
Dynamic: project-url
Dynamic: requires-dist
Dynamic: requires-python
Dynamic: summary
